arcade_slack_api/__init__.py
arcade_slack_api/tools/__init__.py
arcade_slack_api/wrapper_tools/AcceptSlackInvite.json
arcade_slack_api/wrapper_tools/AddCallParticipants.json
arcade_slack_api/wrapper_tools/AddSlackEmojiAlias.json
arcade_slack_api/wrapper_tools/AddSlackReaction.json
arcade_slack_api/wrapper_tools/ApproveSlackChannelInvitation.json
arcade_slack_api/wrapper_tools/CheckApiCallingCode.json
arcade_slack_api/wrapper_tools/CheckSlackDiscoverability.json
arcade_slack_api/wrapper_tools/CreateSlackConversation.json
arcade_slack_api/wrapper_tools/CreateSlackUserGroup.json
arcade_slack_api/wrapper_tools/CustomUnfurlSlackUrls.json
arcade_slack_api/wrapper_tools/DeleteScheduledSlackMessage.json
arcade_slack_api/wrapper_tools/DenySharedInviteRequest.json
arcade_slack_api/wrapper_tools/DisableUserGroup.json
arcade_slack_api/wrapper_tools/EditSlackBookmark.json
arcade_slack_api/wrapper_tools/EnableSlackFileSharing.json
arcade_slack_api/wrapper_tools/EnableSlackUserGroup.json
arcade_slack_api/wrapper_tools/FetchWorkspaceSettingsInfo.json
arcade_slack_api/wrapper_tools/FindSlackUserByEmail.json
arcade_slack_api/wrapper_tools/GetCallInformation.json
arcade_slack_api/wrapper_tools/GetConversationInfo.json
arcade_slack_api/wrapper_tools/GetCurrentSlackTeamInfo.json
arcade_slack_api/wrapper_tools/GetExternalFileUploadUrl.json
arcade_slack_api/wrapper_tools/GetIntegrationLogs.json
arcade_slack_api/wrapper_tools/GetRemoteFileInfoSlack.json
arcade_slack_api/wrapper_tools/GetSlackBotInfo.json
arcade_slack_api/wrapper_tools/GetSlackConversationMembers.json
arcade_slack_api/wrapper_tools/GetSlackMessagePermalink.json
arcade_slack_api/wrapper_tools/GetSlackRemoteFilesInfo.json
arcade_slack_api/wrapper_tools/GetSlackTeamPreferences.json
arcade_slack_api/wrapper_tools/GetSlackThreadMessages.json
arcade_slack_api/wrapper_tools/GetSlackUserPresence.json
arcade_slack_api/wrapper_tools/GetSlackUserProfile.json
arcade_slack_api/wrapper_tools/GetTeamBillableUsersInfo.json
arcade_slack_api-1.0.0.dist-info/METADATA
arcade_slack_api-1.0.0.dist-info/WHEEL
arcade_slack_api-1.0.0.dist-info/entry_points.txt
arcade_slack_api-1.0.0.dist-info/licenses/LICENSE
arcade_slack_api-1.0.0.dist-info/RECORD
